{
    "DataType": "DeaddropQuestData",
    "DataVersion": 0,
    "GameVersion": "0.3.3f14",
    "GUID": "6a2f7361-d9af-4942-8af8-4fbf1a41aea2",
    "State": 2,
    "IsTracked": true,
    "Title": "Collect Dead Drop",
    "Description": "Collect the dead drop at the skate park",
    "Expires": false,
    "ExpiryDate": {
        "DataType": "GameDateTimeData",
        "DataVersion": 0,
        "GameVersion": "0.3.3f14",
        "ElapsedDays": 0,
        "Time": 0
    },
    "Entries": [
        {
            "DataType": "QuestEntryData",
            "DataVersion": 0,
            "GameVersion": "0.3.3f14",
            "Name": "Skate park",
            "State": 2
        }
    ],
    "DeaddropGUID": "eda8c6a4-07be-4d8f-97f4-ddd6dfca19df"
}